xoppylib/__init__.py
xoppylib/fit_gaussian2d.py
xoppylib/mlayer.py
xoppylib/xoppy_run_binaries.py
xoppylib/xoppy_util.py
xoppylib/xoppy_xraylib_util.py
xoppylib/bin/darwin/bfield
xoppylib/bin/darwin/bfield2
xoppylib/bin/darwin/compliance
xoppylib/bin/darwin/diff_pat
xoppylib/bin/darwin/inpro
xoppylib/bin/darwin/mlayer
xoppylib/bin/darwin/srcalc
xoppylib/bin/darwin/tasmip
xoppylib/bin/darwin/tc
xoppylib/bin/darwin/tcap
xoppylib/bin/darwin/txt2u
xoppylib/bin/darwin/u2txt
xoppylib/bin/darwin/urgent
xoppylib/bin/darwin/us
xoppylib/bin/darwin/ws
xoppylib/bin/darwin/xcom
xoppylib/bin/darwin/xpowder_fml
xoppylib/bin/darwin/xtubes
xoppylib/bin/darwin/yaup
xoppylib/bin/linux/bfield
xoppylib/bin/linux/bfield2
xoppylib/bin/linux/complicance
xoppylib/bin/linux/diff_pat
xoppylib/bin/linux/inpro
xoppylib/bin/linux/mlayer
xoppylib/bin/linux/srcalc
xoppylib/bin/linux/tasmip
xoppylib/bin/linux/tc
xoppylib/bin/linux/tcap
xoppylib/bin/linux/txt2u
xoppylib/bin/linux/u2txt
xoppylib/bin/linux/urgent
xoppylib/bin/linux/us
xoppylib/bin/linux/ws
xoppylib/bin/linux/xcom
xoppylib/bin/linux/xpowder_fml
xoppylib/bin/linux/xtubes
xoppylib/bin/linux/yaup
xoppylib/bin/windows/bfield.exe
xoppylib/bin/windows/bfield2.exe
xoppylib/bin/windows/compliance.exe
xoppylib/bin/windows/cryst_ml.exe
xoppylib/bin/windows/cryst_pp.exe
xoppylib/bin/windows/cryst_tt.exe
xoppylib/bin/windows/cryst_za.exe
xoppylib/bin/windows/diff_pat.exe
xoppylib/bin/windows/inpro.exe
xoppylib/bin/windows/mlayer.exe
xoppylib/bin/windows/srcalc.exe
xoppylib/bin/windows/tasmip.exe
xoppylib/bin/windows/tc.exe
xoppylib/bin/windows/tcap.exe
xoppylib/bin/windows/tee.exe
xoppylib/bin/windows/txt2u.exe
xoppylib/bin/windows/u2txt.exe
xoppylib/bin/windows/urgent.exe
xoppylib/bin/windows/us.exe
xoppylib/bin/windows/ws.exe
xoppylib/bin/windows/xcom.exe
xoppylib/bin/windows/xpowder_fml.exe
xoppylib/bin/windows/xtubes.exe
xoppylib/bin/windows/yaup.exe
xoppylib/crystals/__init__.py
xoppylib/crystals/bragg_preprocessor_file_io.py
xoppylib-1.0.53.dist-info/licenses/LICENSE
xoppylib-1.0.53.dist-info/METADATA
xoppylib-1.0.53.dist-info/WHEEL
xoppylib-1.0.53.dist-info/top_level.txt
xoppylib-1.0.53.dist-info/RECORD
