Metadata-Version: 2.4
Name: xoppylib
Version: 1.0.53
Summary: XOPPY library
Home-page: https://github.com/oasys-kit/xoppylib
Download-URL: https://github.com/oasys-kit/xoppylib
Author: Manuel Sanchez del Rio
Author-email: srio@esrf.eu
Maintainer: Manuel Sanchez del Rio
Maintainer-email: srio@esrf.eu
License: MIT
Keywords: x-raysynchrotron radiation,materials x-ray optical constants,Insertion devices,Optical elements,simulation
Classifier: Development Status :: 5 - Production/Stable
Classifier: Environment :: Console
Classifier: Environment :: Plugins
Classifier: Programming Language :: Python :: 3
Classifier: Topic :: Scientific/Engineering :: Visualization
Classifier: Topic :: Software Development :: Libraries :: Python Modules
Classifier: Intended Audience :: Education
Classifier: Intended Audience :: Science/Research
Classifier: Intended Audience :: Developers
License-File: LICENSE
Requires-Dist: setuptools
Requires-Dist: numpy
Requires-Dist: scipy
Requires-Dist: srxraylib>=1.0.67
Requires-Dist: pySRU
Requires-Dist: h5py
Requires-Dist: dabax>=1.0.10
Requires-Dist: crystalpy
Dynamic: author
Dynamic: author-email
Dynamic: classifier
Dynamic: description
Dynamic: download-url
Dynamic: home-page
Dynamic: keywords
Dynamic: license
Dynamic: license-file
Dynamic: maintainer
Dynamic: maintainer-email
Dynamic: requires-dist
Dynamic: summary
